migrations/0001_initial.py
migrations/0002_newslettercampaign_newsletterrecipient.py
migrations/0003_alter_newslettercampaign_options_and_more.py
migrations/0004_alter_newslettercampaign_options_and_more.py
migrations/0005_alter_sendernetsettings_api_key.py
migrations/0006_alter_sendernetsettings_api_key.py
migrations/__init__.py
wagtail_sendernet_extension-0.1.1.dist-info/LICENSE
wagtail_sendernet_extension-0.1.1.dist-info/METADATA
wagtail_sendernet_extension-0.1.1.dist-info/WHEEL
wagtail_sendernet_extension-0.1.1.dist-info/top_level.txt
wagtail_sendernet_extension-0.1.1.dist-info/RECORD
